md410_2023_conv_common/__init__.py
md410_2023_conv_common/build_pdf.py
md410_2023_conv_common/constants.py
md410_2023_conv_common/data.json
md410_2023_conv_common/emailer.py
md410_2023_conv_common/models.py
md410_2023_conv_common/parse_partial_reg_csv.py
md410_2023_conv_common/partial_data.json
md410_2023_conv_common/sqs.py
md410_2023_conv_common/test.pdf
md410_2023_conv_common-2.31.0.dist-info/METADATA
md410_2023_conv_common-2.31.0.dist-info/WHEEL
md410_2023_conv_common-2.31.0.dist-info/RECORD
