Metadata-Version: 2.1
Name: md410-2023-conv-common
Version: 2.31.0
Summary: Common libraries for applications related to the 2023 Lions MD410 Convention
Home-page: https://gitlab.com/md410_2023_conv/md410_2023_conv_common
Author: Kim van Wyk
Author-email: vanwykk@gmail.com
Requires-Python: >=3.7,<4.0
Classifier: Programming Language :: Python :: 3
Classifier: Programming Language :: Python :: 3.7
Classifier: Programming Language :: Python :: 3.8
Classifier: Programming Language :: Python :: 3.9
Classifier: Programming Language :: Python :: 3.10
Classifier: Programming Language :: Python :: 3.11
Requires-Dist: boto3 (>=1.20.3,<2.0.0)
Requires-Dist: click (>=8.0.3,<9.0.0)
Requires-Dist: docker (>=5.0.3,<6.0.0)
Requires-Dist: filetype (>=1.2.0,<2.0.0)
Requires-Dist: pydantic (>=1.8.2,<2.0.0)
Requires-Dist: python-dotenv (>=0.19.2,<0.20.0)
Requires-Dist: redmail (>=0.2.0,<0.3.0)
Requires-Dist: rich (>=13.0.0,<14.0.0)
Requires-Dist: sendgrid (>=6.9.7,<7.0.0)
Project-URL: Repository, https://gitlab.com/md410_2023_conv/md410_2023_conv_common
